enigma_workflow_14.cpython-38-i386-linux-gnu.so
enigma_workflow_14-14.0.66.dist-info/LICENSE
enigma_workflow_14-14.0.66.dist-info/top_level.txt
enigma_workflow_14-14.0.66.dist-info/RECORD
enigma_workflow_14-14.0.66.dist-info/WHEEL
enigma_workflow_14-14.0.66.dist-info/METADATA
enigma_workflow_14.libs/libstdc++-d2a021ba.so.6.0.32
enigma_workflow_14.libs/libgcc_s-f3fb5a36.so.1
