Metadata-Version: 2.1
Name: enigma_workflow_14
Version: 14.0.66
Summary: base module for enigma workflow
Home-page: https://github.com/pybind/enigma_workflow_14
Author: crax
Author-email: 771541803@qq.com
Requires-Python: >=3.7
License-File: LICENSE
